stkai/__init__.py
stkai/_auth.py
stkai/_cli.py
stkai/_config.py
stkai/_http.py
stkai/_rate_limit.py
stkai/_retry.py
stkai/_utils.py
stkai/agents/__init__.py
stkai/agents/_agent.py
stkai/agents/_handlers.py
stkai/agents/_models.py
stkai/rqc/__init__.py
stkai/rqc/_event_listeners.py
stkai/rqc/_handlers.py
stkai/rqc/_models.py
stkai/rqc/_remote_quick_command.py
stkai-0.4.6.dist-info/licenses/LICENSE
stkai-0.4.6.dist-info/METADATA
stkai-0.4.6.dist-info/WHEEL
stkai-0.4.6.dist-info/top_level.txt
stkai-0.4.6.dist-info/RECORD
