Metadata-Version: 2.4
Name: stkai
Version: 0.4.6
Summary: Python SDK for StackSpot AI - Remote Quick Commands and more
Author-email: Rafael Ponte <rponte@gmail.com>
License: Apache-2.0
Project-URL: Homepage, https://github.com/rafaelpontezup/stkai-sdk-python
Project-URL: Documentation, https://rafaelpontezup.github.io/stkai-sdk-python/
Project-URL: Repository, https://github.com/rafaelpontezup/stkai-sdk-python
Project-URL: Issues, https://github.com/rafaelpontezup/stkai-sdk-python/issues
Keywords: stackspot,ai,sdk,quick-commands,llm,agents,api client
Classifier: Development Status :: 3 - Alpha
Classifier: Intended Audience :: Developers
Classifier: License :: OSI Approved :: Apache Software License
Classifier: Operating System :: OS Independent
Classifier: Programming Language :: Python :: 3
Classifier: Programming Language :: Python :: 3.12
Classifier: Programming Language :: Python :: 3.13
Classifier: Topic :: Software Development :: Libraries :: Python Modules
Classifier: Typing :: Typed
Requires-Python: >=3.12
License-File: LICENSE
Requires-Dist: requests>=2.28.0
Provides-Extra: dev
Requires-Dist: pytest>=7.0.0; extra == "dev"
Requires-Dist: pytest-cov>=4.0.0; extra == "dev"
Requires-Dist: coverage>=5.0.0; extra == "dev"
Requires-Dist: mypy>=1.0.0; extra == "dev"
Requires-Dist: ruff>=0.1.0; extra == "dev"
Requires-Dist: types-requests>=2.28.0; extra == "dev"
Provides-Extra: docs
Requires-Dist: mkdocs>=1.5.0; extra == "docs"
Requires-Dist: mkdocs-material>=9.5.0; extra == "docs"
Requires-Dist: mkdocstrings[python]>=0.24.0; extra == "docs"
Requires-Dist: mkdocs-gen-files>=0.5.0; extra == "docs"
Requires-Dist: mkdocs-literate-nav>=0.6.0; extra == "docs"
Dynamic: license-file
